gsf/__init__.py
gsf/binarystream.py
gsf/encoding7bit.py
gsf/endianorder.py
gsf/streamencoder.py
sttp/__init__.py
sttp/config.py
sttp/reader.py
sttp/settings.py
sttp/subscriber.py
sttp/ticks.py
sttp/version.py
sttp/data/__init__.py
sttp/data/callbackerrorlistener.py
sttp/data/columnexpression.py
sttp/data/constants.py
sttp/data/datacolumn.py
sttp/data/datarow.py
sttp/data/dataset.py
sttp/data/datatable.py
sttp/data/datatype.py
sttp/data/errors.py
sttp/data/expression.py
sttp/data/expressiontree.py
sttp/data/filterexpressionparser.py
sttp/data/functionexpression.py
sttp/data/inlistexpression.py
sttp/data/operatorexpression.py
sttp/data/orderbyterm.py
sttp/data/tableidfields.py
sttp/data/unaryexpression.py
sttp/data/valueexpression.py
sttp/metadata/__init__.py
sttp/metadata/cache.py
sttp/metadata/record/__init__.py
sttp/metadata/record/device.py
sttp/metadata/record/measurement.py
sttp/metadata/record/phasor.py
sttp/transport/__init__.py
sttp/transport/bufferblock.py
sttp/transport/compactmeasurement.py
sttp/transport/constants.py
sttp/transport/datasubscriber.py
sttp/transport/measurement.py
sttp/transport/signalindexcache.py
sttp/transport/signalkind.py
sttp/transport/subscriberconnector.py
sttp/transport/subscriptioninfo.py
sttp/transport/tssc/__init__.py
sttp/transport/tssc/decoder.py
sttp/transport/tssc/pointmetadata.py
sttpapi-0.6.4.dist-info/LICENSE
sttpapi-0.6.4.dist-info/METADATA
sttpapi-0.6.4.dist-info/WHEEL
sttpapi-0.6.4.dist-info/top_level.txt
sttpapi-0.6.4.dist-info/RECORD
