Metadata-Version: 2.1
Name: sttpapi
Version: 0.6.4
Summary: Streaming Telemetry Transport Protocol API
Home-page: https://github.com/sttp/pyapi
Download-URL: https://pypi.org/project/sttpapi/
Author: J. Ritchie Carroll
Author-email: rcarroll@gridprotectionalliance.org
Project-URL: Bug Tracker, https://github.com/sttp/pyapi/issues
Project-URL: Documentation, https://sttp.github.io/pyapi/
Project-URL: Source Code, https://github.com/sttp/pyapi
Keywords: STTP,IEEE 2664,streaming,telemetry,time-series,protocol,synchrophasor
Classifier: Development Status :: 5 - Production/Stable
Classifier: Intended Audience :: Science/Research
Classifier: Intended Audience :: Developers
Classifier: Topic :: Scientific/Engineering :: Interface Engine/Protocol Translator
Classifier: Programming Language :: Python :: 3.9
Classifier: License :: OSI Approved :: MIT License
Classifier: Operating System :: OS Independent
Requires-Python: >=3.9
License-File: LICENSE
Requires-Dist: numpy>=1.22
Requires-Dist: pycryptodome>=3.15.0
Requires-Dist: python-dateutil>=2.8.2
Requires-Dist: antlr4-python3-runtime>=4.13
